griptape/__init__.py
griptape/core/__init__.py
griptape/core/adapters/__init__.py
griptape/core/adapters/chatgpt_plugin_adapter.py
griptape/core/adapters/langchain_tool_adapter.py
griptape/core/base_adapter.py
griptape/core/base_executor.py
griptape/core/base_tool.py
griptape/core/decorators.py
griptape/core/executors/__init__.py
griptape/core/executors/docker_executor.py
griptape/core/executors/local_executor.py
griptape/core/resources/chatgpt_plugin_adapter/ai-plugin.json.j2
griptape/core/resources/docker_executor/Dockerfile
griptape/core/utils/__init__.py
griptape/core/utils/command_runner.py
griptape/core/utils/j2.py
griptape/core/utils/manifest_validator.py
griptape/core/utils/python_runner.py
griptape_core-0.9.3.dist-info/LICENSE
griptape_core-0.9.3.dist-info/METADATA
griptape_core-0.9.3.dist-info/WHEEL
griptape_core-0.9.3.dist-info/RECORD
