Metadata-Version: 2.1
Name: griptape-core
Version: 0.9.3
Summary: Python framework for LLM middleware tools. Build once, run anywhere.
Home-page: https://github.com/griptape-ai/griptape-core
License: Apache 2.0
Author: Griptape
Author-email: hello@griptape.ai
Requires-Python: >=3.9,<4.0
Classifier: License :: Other/Proprietary License
Classifier: Programming Language :: Python :: 3
Classifier: Programming Language :: Python :: 3.9
Classifier: Programming Language :: Python :: 3.10
Classifier: Programming Language :: Python :: 3.11
Requires-Dist: attrs (>=22)
Requires-Dist: docker (>=6)
Requires-Dist: fastapi (>=0.80)
Requires-Dist: jinja2 (>=3.1)
Requires-Dist: langchain (>=0.0.120)
Requires-Dist: openai (>=0.27)
Requires-Dist: python-decouple (>=3)
Requires-Dist: pyyaml (>=6)
Requires-Dist: schema (>=0.7)
Requires-Dist: stringcase (>=1)
Requires-Dist: uvicorn (>=0.20)
Project-URL: Repository, https://github.com/griptape-ai/griptape-core
